zetasql/__init__.py
zetasql/__version__.py
zetasql/api/__init__.py
zetasql/api/analyzer.py
zetasql/api/ast_visitor.py
zetasql/api/parser.py
zetasql/api/prepared_expression.py
zetasql/api/prepared_query.py
zetasql/api/resolved_visitor.py
zetasql/api/table_content.py
zetasql/api/tree_visitor.py
zetasql/api/type_factory.py
zetasql/api/value.py
zetasql/api/builders/__init__.py
zetasql/api/builders/_helpers.py
zetasql/api/builders/catalog_builder.py
zetasql/api/builders/constant_builder.py
zetasql/api/builders/function_builder.py
zetasql/api/builders/table_builder.py
zetasql/api/builders/tvf_builder.py
zetasql/core/__init__.py
zetasql/core/exceptions.py
zetasql/core/func_utils.py
zetasql/core/local_service.py
zetasql/core/wasm_client.py
zetasql/types/__init__.py
zetasql/types/proto_model/__init__.py
zetasql/types/proto_model/generated.py
zetasql/types/proto_model/proto_model.py
zetasql/types/proto_model/extensions/__init__.py
zetasql/types/proto_model/extensions/language_options.py
zetasql/types/proto_model/extensions/simple_catalog.py
zetasql/types/proto_model/extensions/type.py
zetasql/types/proto_model/mixins/__init__.py
zetasql/types/proto_model/mixins/type_kind.py
zetasql/wasi/__init__.py
zetasql/wasi/zetasql.wasm
zetasql/wasi/_pb2/__init__.py
zetasql/wasi/_pb2/zetasql/__init__.py
zetasql/wasi/_pb2/zetasql/common/__init__.py
zetasql/wasi/_pb2/zetasql/common/reflection_pb2.py
zetasql/wasi/_pb2/zetasql/common/reflection_pb2.pyi
zetasql/wasi/_pb2/zetasql/common/match_recognize/__init__.py
zetasql/wasi/_pb2/zetasql/common/match_recognize/match_test_result_pb2.py
zetasql/wasi/_pb2/zetasql/common/match_recognize/match_test_result_pb2.pyi
zetasql/wasi/_pb2/zetasql/compliance/__init__.py
zetasql/wasi/_pb2/zetasql/compliance/compliance_label_pb2.py
zetasql/wasi/_pb2/zetasql/compliance/compliance_label_pb2.pyi
zetasql/wasi/_pb2/zetasql/compliance/known_error_pb2.py
zetasql/wasi/_pb2/zetasql/compliance/known_error_pb2.pyi
zetasql/wasi/_pb2/zetasql/local_service/__init__.py
zetasql-0.1.5.dist-info/licenses/LICENSE
zetasql-0.1.5.dist-info/METADATA
zetasql-0.1.5.dist-info/WHEEL
zetasql-0.1.5.dist-info/top_level.txt
zetasql-0.1.5.dist-info/RECORD
