Metadata-Version: 2.4
Name: zetasql
Version: 0.1.5
Summary: Python port of Google's ZetaSQL - SQL analysis and parsing library
Author-email: Hyun Heo <h0h6h2h5@gmail.com>
Maintainer-email: Hyun Heo <h0h6h2h5@gmail.com>
License: Apache-2.0
Project-URL: Homepage, https://github.com/heoh/zetasql-py
Project-URL: Repository, https://github.com/heoh/zetasql-py
Project-URL: Issues, https://github.com/heoh/zetasql-py/issues
Keywords: sql,parser,zetasql,query,analysis
Classifier: Development Status :: 3 - Alpha
Classifier: Intended Audience :: Developers
Classifier: License :: OSI Approved :: Apache Software License
Classifier: Operating System :: OS Independent
Classifier: Programming Language :: Python :: 3
Classifier: Programming Language :: Python :: 3.10
Classifier: Programming Language :: Python :: 3.11
Classifier: Programming Language :: Python :: 3.12
Classifier: Programming Language :: Python :: 3.13
Classifier: Programming Language :: Python :: 3.14
Classifier: Topic :: Database
Classifier: Topic :: Software Development :: Libraries :: Python Modules
Classifier: Typing :: Typed
Requires-Python: >=3.10
License-File: LICENSE
Requires-Dist: wasmtime>=24.0.0
Requires-Dist: grpcio>=1.60.0
Requires-Dist: protobuf>=6.31.1
Requires-Dist: tzdata>=2020.1
Provides-Extra: dev
Requires-Dist: pytest>=7.0.0; extra == "dev"
Requires-Dist: pytest-cov>=4.0.0; extra == "dev"
Requires-Dist: grpcio-tools>=1.60.0; extra == "dev"
Requires-Dist: ruff>=0.14.0; extra == "dev"
Dynamic: license-file
